.gitignore
CODE_OF_CONDUCT.md
LICENSE.txt
MANIFEST.in
README.md
VERSION
conda.yaml
pytest.ini
setup.py
.github/workflows/deploy.yml
.github/workflows/stylecheck.yml
.github/workflows/test.yml
.idea/.gitignore
dask_sql/__init__.py
dask_sql/context.py
dask_sql/java.py
dask_sql/mappings.py
dask_sql/utils.py
dask_sql/jar/DaskSQL.jar
dask_sql/physical/__init__.py
dask_sql/physical/rel/__init__.py
dask_sql/physical/rel/base.py
dask_sql/physical/rel/convert.py
dask_sql/physical/rel/logical/__init__.py
dask_sql/physical/rel/logical/aggregate.py
dask_sql/physical/rel/logical/filter.py
dask_sql/physical/rel/logical/join.py
dask_sql/physical/rel/logical/project.py
dask_sql/physical/rel/logical/sort.py
dask_sql/physical/rel/logical/table_scan.py
dask_sql/physical/rel/logical/union.py
dask_sql/physical/rel/logical/values.py
dask_sql/physical/rex/__init__.py
dask_sql/physical/rex/base.py
dask_sql/physical/rex/convert.py
dask_sql/physical/rex/core/__init__.py
dask_sql/physical/rex/core/call.py
dask_sql/physical/rex/core/input_ref.py
dask_sql/physical/rex/core/literal.py
dask_sql/server/__init__.py
dask_sql/server/handler.py
dask_sql/server/messages.py
mason_dask_sql.egg-info/PKG-INFO
mason_dask_sql.egg-info/SOURCES.txt
mason_dask_sql.egg-info/dependency_links.txt
mason_dask_sql.egg-info/not-zip-safe
mason_dask_sql.egg-info/requires.txt
mason_dask_sql.egg-info/top_level.txt
planner/pom.xml
planner/src/main/java/com/dask/sql/application/RelationalAlgebraGenerator.java
planner/src/main/java/com/dask/sql/schema/DaskSchema.java
planner/src/main/java/com/dask/sql/schema/DaskTable.java
planner/src/main/resources/log4j.xml
tests/__init__.py
tests/integration/fixtures.py
tests/integration/test_filter.py
tests/integration/test_groupby.py
tests/integration/test_join.py
tests/integration/test_rex.py
tests/integration/test_select.py
tests/integration/test_sort.py
tests/integration/test_sqlite.py
tests/integration/test_union.py
tests/unit/test_mapping.py
tests/unit/test_utils.py