Metadata-Version: 1.2
Name: mason-dask-sql
Version: 0.1.3
Summary: Dask SQL
Home-page: http://github.com/nils-braun/dask-sql/
Maintainer: Nils Braun
Maintainer-email: nilslennartbraun@gmail.com
License: MIT
Platform: UNKNOWN
Requires-Python: >=3.6
